libmeshctrl-1.3.2.dist-info/licenses/LICENSE.txt
meshctrl/__init__.py
meshctrl/constants.py
meshctrl/device.py
meshctrl/exceptions.py
meshctrl/files.py
meshctrl/mesh.py
meshctrl/session.py
meshctrl/shell.py
meshctrl/tunnel.py
meshctrl/types.py
meshctrl/user_group.py
meshctrl/util.py
libmeshctrl-1.3.2.dist-info/METADATA
libmeshctrl-1.3.2.dist-info/WHEEL
libmeshctrl-1.3.2.dist-info/top_level.txt
libmeshctrl-1.3.2.dist-info/RECORD
