Metadata-Version: 2.4
Name: libmeshctrl
Version: 1.3.2
Summary: Python package for interacting with a Meshcentral server instance
Home-page: https://github.com/HuFlungDu/pylibmeshctrl/
Author: Josiah Baldwin
Author-email: jbaldwin8889@gmail.com
License: MIT
Project-URL: Documentation, https://pylibmeshctrl.readthedocs.io/
Project-URL: Source, https://github.com/HuFlungDu/pylibmeshctrl/
Platform: any
Classifier: Development Status :: 5 - Production/Stable
Classifier: Programming Language :: Python
Requires-Python: >=3.8
License-File: LICENSE.txt
Requires-Dist: importlib-metadata
Requires-Dist: cryptography~=44.0.1
Requires-Dist: websockets~=15.0.0
Requires-Dist: python-socks[asyncio]~=2.5.3
Provides-Extra: testing
Requires-Dist: setuptools; extra == "testing"
Requires-Dist: pytest; extra == "testing"
Requires-Dist: pytest-cov; extra == "testing"
Dynamic: license-file
